	<string id="tips_agr_krot_sos">
		<text>Aiuto! Mi sentite?! I militari ci hanno inchiodato alla fabbrica!</text>
	</string>
	<string id="tips_agr_krot_sos1">
		<text>Quei maiali mi hanno accerchiato nel cortile. Aiuto!</text>
	</string>
	<string id="tips_agr_krot_sos2">
		<text>Tutti i mei uomini sono caduti!</text>
	</string>
	<string id="tips_agr_stalker_help_1">
		<text>.....</text>
	</string>
	<string id="tips_agr_stalker_help_2">
		<text>.....</text>
	</string>
	<string id="tips_agr_trader_documents">
		<text>Fila via, Marchiato. Non riuscirai a superare quei bastardi di militari senza combattere. Ho parlato di te al Barista. Farà un accordo con i Duty, e ti lasceranno passare.</text>
	</string>
	<string id="tips_captain_name">
		<text>Capitano Maximenko</text>
	</string>
	<string id="ghost_tips">
		<text>Strelok, ci sono brutte notizie. Zanna è morto. Non è riuscito a incontrati. Peccato che sei andato al centro della Zona da solo. Però è stata una tua scelta. So dove cercarti e a chi chiedere. Fantasma.</text>
	</string>
